donuts/__init__.py
donuts/_astropy_init.py
donuts/conftest.py
donuts/donuts.py
donuts/image.py
donuts/version.py
donuts/tests/__init__.py
donuts/tests/coveragerc
donuts/tests/helpers.py
donuts/tests/setup_package.py
donuts/tests/synthetic_data.py
donuts/tests/test_choosing_image_class.py
donuts/tests/test_donuts_with_synthetic_data.py
donuts/tests/test_image.py
donuts/tests/test_integration.py
donuts/tests/test_integration2.py
donuts/tests/test_read_image.py
donuts/tests/test_summary.py
donuts/tests/test_synthetic_data.py
donuts-0.4.0.dist-info/METADATA
donuts-0.4.0.dist-info/WHEEL
donuts-0.4.0.dist-info/top_level.txt
donuts-0.4.0.dist-info/RECORD
